{
  "name": "Chewtle",
  "nationalPokedexNumber": 833,
  "primaryType": "water",
  "abilities": [
    "strongjaw",
    "shellarmor",
    "h:swiftswim"
  ],
  "baseStats": {
    "hp": 50,
    "attack": 64,
    "defence": 50,
    "special_attack": 38,
    "special_defence": 38,
    "speed": 44
  },
  "catchRate": 255,
  "maleRatio": 0.5,
  "shoulderMountable": false,
  "baseExperienceYield": 57,
  "experienceGroup": "medium_fast",
  "eggCycles": 20,
  "eggGroups": [
    "monster",
    "water_1"
  ],
  "moves": [
    "1:tackle",
    "1:watergun",
    "7:bite",
    "14:protect",
    "21:headbutt",
    "28:counter",
    "35:jawlock",
    "42:liquidation",
    "49:bodyslam",
    "100:dragontail",
    "100:gastroacid",
    "100:shellsmash",
    "100:skullbash",
    "100:assurance",
    "100:attract",
    "100:bodyslam",
    "100:chillingwater",
    "100:crunch",
    "100:dive",
    "100:dragontail",
    "100:endure",
    "100:facade",
    "100:falseswipe",
    "100:hydropump",
    "100:icefang",
    "100:liquidation",
    "100:mudshot",
    "100:payback",
    "100:poisonjab",
    "100:protect",
    "100:raindance",
    "100:rest",
    "100:revenge",
    "100:round",
    "100:scaryface",
    "100:sleeptalk",
    "100:snore",
    "100:stompingtantrum",
    "100:substitute",
    "100:surf",
    "100:takedown",
    "100:terablast",
    "100:waterfall",
    "100:waterpulse",
    "100:whirlpool",
    "100:scaleshot",
    "100:skittersmack"
  ],
  "labels": [
    "gen8"
  ],
  "pokedex": [
    "cobblemon.species.chewtle.desc"
  ],
  "evolutions": [
    {
      "id": "chewtle_drednaw",
      "variant": "level_up",
      "result": "drednaw",
      "consumeHeldItem": false,
      "learnableMoves": [
        "rocktomb"
      ],
      "requirements": [
        {
          "variant": "level",
          "minLevel": 22
        }
      ]
    }
  ],
  "baseScale": 1,
  "hitbox": {
    "width": 1,
    "height": 1,
    "fixed": false
  },
  "baseFriendship": 50,
  "evYield": {
    "hp": 0,
    "attack": 1,
    "defence": 0,
    "special_attack": 0,
    "special_defence": 0,
    "speed": 0
  },
  "height": 3,
  "weight": 85,
  "aspects": [],
  "cannotDynamax": false
}