{
  "name": "Dracovish",
  "nationalPokedexNumber": 882,
  "primaryType": "water",
  "secondaryType": "dragon",
  "abilities": [
    "waterabsorb",
    "strongjaw",
    "h:sandrush"
  ],
  "baseStats": {
    "hp": 90,
    "attack": 90,
    "defence": 100,
    "special_attack": 70,
    "special_defence": 80,
    "speed": 75
  },
  "catchRate": 45,
  "maleRatio": -1,
  "shoulderMountable": false,
  "baseExperienceYield": 177,
  "experienceGroup": "slow",
  "eggCycles": 35,
  "eggGroups": [
    "undiscovered"
  ],
  "moves": [
    "1:tackle",
    "1:watergun",
    "7:protect",
    "14:brutalswing",
    "21:ancientpower",
    "28:bite",
    "35:dragonbreath",
    "42:stomp",
    "49:superfang",
    "56:crunch",
    "63:fishiousrend",
    "70:dragonpulse",
    "77:dragonrush",
    "100:bodyslam",
    "100:brine",
    "100:brutalswing",
    "100:bulldoze",
    "100:crunch",
    "100:dive",
    "100:dragonpulse",
    "100:earthpower",
    "100:earthquake",
    "100:endure",
    "100:facade",
    "100:gigaimpact",
    "100:hydropump",
    "100:hyperbeam",
    "100:icefang",
    "100:ironhead",
    "100:leechlife",
    "100:liquidation",
    "100:lowkick",
    "100:megakick",
    "100:outrage",
    "100:protect",
    "100:psychicfangs",
    "100:raindance",
    "100:rest",
    "100:rockblast",
    "100:rockslide",
    "100:rocktomb",
    "100:round",
    "100:scald",
    "100:sleeptalk",
    "100:snore",
    "100:stompingtantrum",
    "100:stoneedge",
    "100:substitute",
    "100:surf",
    "100:waterfall",
    "100:whirlpool",
    "100:zenheadbutt",
    "100:dracometeor",
    "100:dragonrush",
    "100:fishiousrend",
    "100:icefang",
    "100:meteorbeam",
    "100:protect",
    "100:tackle",
    "100:watergun"
  ],
  "labels": [
    "gen8"
  ],
  "pokedex": [
    "cobblemon.species.dracovish.desc"
  ],
  "evolutions": [],
  "baseScale": 1,
  "hitbox": {
    "width": 1,
    "height": 1,
    "fixed": false
  },
  "baseFriendship": 50,
  "evYield": {
    "hp": 0,
    "attack": 0,
    "defence": 2,
    "special_attack": 0,
    "special_defence": 0,
    "speed": 0
  },
  "height": 23,
  "weight": 2150,
  "aspects": [],
  "cannotDynamax": false
}